Flightaware.py
AkerFlight-0.1.dist-info/LICENSE.txt
AkerFlight-0.1.dist-info/METADATA
AkerFlight-0.1.dist-info/WHEEL
AkerFlight-0.1.dist-info/top_level.txt
AkerFlight-0.1.dist-info/RECORD
